MANIFEST.in
README.rst
pbh-clean
pbh-harvest
pbh-prepare
pbh-umbrella
setup.cfg
setup.py
versioneer.py
pert_belly_hack/__init__.py
pert_belly_hack/_version.py
pert_belly_hack/defaults.py
pert_belly_hack/harvesting.py
pert_belly_hack/packaging.py
pert_belly_hack/umbrella_index.py
pert_belly_hack.egg-info/PKG-INFO
pert_belly_hack.egg-info/SOURCES.txt
pert_belly_hack.egg-info/dependency_links.txt
pert_belly_hack.egg-info/top_level.txt
pert_belly_hack/templates/control
pert_belly_hack/templates/github_io.conf
pert_belly_hack/templates/index.html
pert_belly_hack/templates/opkg_filename
pert_belly_hack/templates/umbrella.html