Metadata-Version: 1.0
Name: pert-belly-hack
Version: 1.3.2
Summary: Packaging helper for preparing the contents of an OPKG file containing a web interface for enigma2 devices.Also generates contents for github pages.
Home-page: https://doubleo8.github.io/e2openplugin-OpenWebif/
Author: doubleO8
Author-email: wb008@hdm-stuttgart.de
License: UNKNOWN
Platform: UNKNOWN
